arcproxyutilities/__init__.py
arcproxyutilities/_utils.py
arcproxyutilities/constants.py
arcproxyutilities/csputility.py
arcproxyutilities-1.0.5.dist-info/License.txt
arcproxyutilities-1.0.5.dist-info/METADATA
arcproxyutilities-1.0.5.dist-info/WHEEL
arcproxyutilities-1.0.5.dist-info/top_level.txt
arcproxyutilities-1.0.5.dist-info/RECORD
