Metadata-Version: 2.1
Name: arcproxyutilities
Version: 1.0.5
Summary: Arc proxy utilities for provisioned clusters
Home-page: https://msazure.visualstudio.com/CloudNativeCompute/_git/ArcProxyUtilities
Author: Microsoft Corporation
Author-email: k8connect@microsoft.com
License: MIT
Platform: UNKNOWN
Classifier: Development Status :: 4 - Beta
Classifier: Intended Audience :: Developers
Classifier: Intended Audience :: System Administrators
Classifier: Programming Language :: Python
Classifier: Programming Language :: Python :: 3
Classifier: Programming Language :: Python :: 3.6
Classifier: Programming Language :: Python :: 3.7
Classifier: Programming Language :: Python :: 3.8
Classifier: License :: OSI Approved :: MIT License
License-File: License.txt
Requires-Dist: kubernetes (==11.0.0)
Requires-Dist: pycryptodome (==3.12.0)
